krakee/Krakee.py
krakee/__init__.py
krakee/api/OrderBuilder.py
krakee/api/PrettyNames.py
krakee/api/__init__.py
krakee/api/utils.py
krakee/api/validators.py
krakee/types/AssetDataFrame.py
krakee/types/OhlcDataFrame.py
krakee/types/TickerDataFrame.py
krakee/types/__init__.py
krapanda/Krapanda.py
krapanda/__init__.py
krapanda/krapanda.py
krapanda/api/OrderBuilder.py
krapanda/api/PrivateApi.py
krapanda/api/PublicApi.py
krapanda/api/__init__.py
krakee-0.9.7.dist-info/LICENSE
krakee-0.9.7.dist-info/METADATA
krakee-0.9.7.dist-info/WHEEL
krakee-0.9.7.dist-info/top_level.txt
krakee-0.9.7.dist-info/RECORD
