Metadata-Version: 2.1
Name: krakee
Version: 0.9.7
Summary: Kraken Exchange API with a thin pandas Dataframe wrap
Home-page: https://github.com/rubenafo/krakee
Author: Ruben Afonso
Author-email: rbfrancos@gmail.com
License: UNKNOWN
Keywords: kraken,cryptocurrencies,exchange,python,bitcoin,trading,crypto
Platform: UNKNOWN
Classifier: Programming Language :: Python :: 3
Classifier: License :: OSI Approved :: Apache Software License
Classifier: Operating System :: OS Independent
Requires-Python: >=3.7
Requires-Dist: krakenex
Requires-Dist: pandas
Requires-Dist: pykrakenapi
